caterpillard/__init__.py
caterpillard/caterpillar.py
caterpillard/data/cd_input_data.csv
caterpillard-0.0.4.dist-info/LICENSE
caterpillard-0.0.4.dist-info/METADATA
caterpillard-0.0.4.dist-info/WHEEL
caterpillard-0.0.4.dist-info/top_level.txt
caterpillard-0.0.4.dist-info/RECORD
