Metadata-Version: 2.1
Name: caterpillard
Version: 0.0.4
Summary: Caterpillar Diagram
Author-email: Prabal Pratap Singh <mechaprabal@gmail.com>, Deepu Philip <dphilip@iitk.ac.in>
License: GNU AFFERO GENERAL PUBLIC LICENSE
Project-URL: Homepage, https://github.com/mechaprabal/caterpillard
Project-URL: Bug Tracker, https://github.com/mechaprabal/caterpillard/issues
Classifier: Programming Language :: Python :: 3
Classifier: License :: OSI Approved :: GNU Affero General Public License v3
Classifier: Operating System :: OS Independent
Requires-Python: >=3.7
License-File: LICENSE
Requires-Dist: numpy
Requires-Dist: pandas
Requires-Dist: matplotlib
Requires-Dist: progressbar2
Provides-Extra: docs
Requires-Dist: autopep8 ; extra == 'docs'
Requires-Dist: flake8 ; extra == 'docs'
Requires-Dist: black ; extra == 'docs'
Requires-Dist: sphinx ; extra == 'docs'
Requires-Dist: myst-parser ; extra == 'docs'
Requires-Dist: sphinx-autobuild ; extra == 'docs'
Requires-Dist: furo ; extra == 'docs'
Requires-Dist: nbsphinx ; extra == 'docs'
Provides-Extra: tests
Requires-Dist: autopep8 ; extra == 'tests'
Requires-Dist: flake8 ; extra == 'tests'
Requires-Dist: black ; extra == 'tests'
Requires-Dist: pytest ; extra == 'tests'
